sample/__init__.py
sample/constants.py
sample/data/CBOE.py
sample/data/EUREX.py
sample/data/__init__.py
sample/data/implied_data.py
sample/data/market_data.py
sample/hedging/__init__.py
sample/hedging/hedging.py
sample/models/__init__.py
sample/models/bi_black_scholes_model/__init__.py
sample/models/bi_black_scholes_model/model.py
sample/models/bi_black_scholes_model/parameters.py
sample/models/black_scholes_model/__init__.py
sample/models/black_scholes_model/model.py
sample/models/black_scholes_model/parameters.py
sample/models/black_scholes_term_structure_model/__init__.py
sample/models/black_scholes_term_structure_model/calibration.py
sample/models/black_scholes_term_structure_model/model.py
sample/models/heston_model/__init__.py
sample/models/heston_model/calibration.py
sample/models/heston_model/model.py
sample/models/heston_model/parameters.py
sample/models/local_volatility_model/__init__.py
sample/models/local_volatility_model/calibration.py
sample/models/local_volatility_model/model.py
sample/models/multi_black_scholes_model/__init__.py
sample/models/multi_black_scholes_model/model.py
sample/models/multi_black_scholes_model/parameters.py
sample/pricing/__init__.py
sample/pricing/european_bi_option.py
sample/pricing/option.py
sample/pricing/american_single_option/__init__.py
sample/pricing/american_single_option/american_option_black_scholes_pricing.py
sample/pricing/american_single_option/american_option_pricing.py
sample/pricing/asian_single_option/__init__.py
sample/pricing/asian_single_option/asian_single_option.py
sample/pricing/european_basket_option/__init__.py
sample/pricing/european_basket_option/european_basket_option.py
sample/pricing/european_single_option/__init__.py
sample/pricing/european_single_option/european_single_option.py
sample/products/__init__.py
sample/products/european_bi_option.py
sample/products/option.py
sample/products/american_single_option/__init__.py
XCorVar-0.1.2.dist-info/LICENCE.txt
XCorVar-0.1.2.dist-info/METADATA
XCorVar-0.1.2.dist-info/WHEEL
XCorVar-0.1.2.dist-info/top_level.txt
XCorVar-0.1.2.dist-info/RECORD
