Metadata-Version: 2.1
Name: XCorVar
Version: 0.1.2
Summary: Quantitative Analysis Library
Home-page: https://github.com/matt-charr/XCorVar
Author: Matthieu Charrier
Author-email: matthieu.charrier.pro@gmail.com
License: MIT
Platform: UNKNOWN
Classifier: License :: OSI Approved :: MIT License
Classifier: Programming Language :: Python
Classifier: Programming Language :: Python :: 3
Classifier: Programming Language :: Python :: 3.6
Classifier: Programming Language :: Python :: Implementation :: CPython
Classifier: Programming Language :: Python :: Implementation :: PyPy
Requires-Python: >=3.9.0
Requires-Dist: scipy
